agent_uri/__init__.py
agent_uri/auth.py
agent_uri/capability.py
agent_uri/cli.py
agent_uri/client.py
agent_uri/common/__init__.py
agent_uri/common/error/__init__.py
agent_uri/common/error/models.py
agent_uri/common/error/transport.py
agent_uri/common/tests/__init__.py
agent_uri/common/tests/test_error_models.py
agent_uri/common/tests/test_error_transport.py
agent_uri/descriptor/__init__.py
agent_uri/descriptor/compatibility.py
agent_uri/descriptor/generator.py
agent_uri/descriptor/models.py
agent_uri/descriptor/parser.py
agent_uri/descriptor/tests/__init__.py
agent_uri/descriptor/tests/test_compatibility.py
agent_uri/descriptor/tests/test_parser.py
agent_uri/descriptor/tests/test_validator.py
agent_uri/descriptor/validator.py
agent_uri/exceptions.py
agent_uri/handler.py
agent_uri/parser.py
agent_uri/resolver/__init__.py
agent_uri/resolver/cache.py
agent_uri/resolver/resolver.py
agent_uri/resolver/tests/__init__.py
agent_uri/resolver/tests/test_caching.py
agent_uri/resolver/tests/test_resolver.py
agent_uri/server.py
agent_uri/tests/__init__.py
agent_uri/tests/test_auth.py
agent_uri/tests/test_basic.py
agent_uri/tests/test_capability.py
agent_uri/tests/test_cli.py
agent_uri/tests/test_client.py
agent_uri/tests/test_exceptions.py
agent_uri/tests/test_parser.py
agent_uri/tests/test_server.py
agent_uri/tests/test_server_edge_cases.py
agent_uri/tests/test_server_fastapi_detailed.py
agent_uri/transport/__init__.py
agent_uri/transport/base.py
agent_uri/transport/registry.py
agent_uri/transport/tests/__init__.py
agent_uri/transport/tests/test_https_transport.py
agent_uri/transport/tests/test_local_execution.py
agent_uri/transport/tests/test_local_import_handling.py
agent_uri/transport/tests/test_local_socket_handling.py
agent_uri/transport/tests/test_local_transport.py
agent_uri/transport/tests/test_registry.py
agent_uri/transport/tests/test_websocket_connection.py
agent_uri/transport/tests/test_websocket_error_handling.py
agent_uri-0.3.0.dist-info/LICENSE
agent_uri-0.3.0.dist-info/METADATA
agent_uri-0.3.0.dist-info/WHEEL
agent_uri-0.3.0.dist-info/entry_points.txt
agent_uri-0.3.0.dist-info/RECORD
