Metadata-Version: 2.3
Name: agent-uri
Version: 0.3.0
Summary: Agent URI Protocol Implementation - A complete suite for addressing and interacting with AI agents
License: BSD-3-Clause
Keywords: agent,uri,protocol,ai,rfc
Author: Yaswanth Narvaneni
Author-email: yaswanth@gmail.com
Requires-Python: >=3.9.2,<4.0
Classifier: Development Status :: 3 - Alpha
Classifier: Intended Audience :: Developers
Classifier: License :: OSI Approved :: BSD License
Classifier: Programming Language :: Python :: 3
Classifier: Programming Language :: Python :: 3.10
Classifier: Programming Language :: Python :: 3.11
Classifier: Programming Language :: Python :: 3.12
Classifier: Programming Language :: Python :: 3.13
Classifier: Programming Language :: Python :: 3.9
Classifier: Topic :: Internet :: WWW/HTTP
Classifier: Topic :: Software Development :: Libraries :: Python Modules
Classifier: Topic :: System :: Networking
Requires-Dist: anyio (>=4.9.0,<5.0.0)
Requires-Dist: cryptography (>=45.0.4,<46.0.0)
Requires-Dist: fastapi (>=0.115.0,<0.116.0)
Requires-Dist: jsonschema (>=4.20.0,<5.0.0)
Requires-Dist: pydantic (>=2.5.0,<3.0.0)
Requires-Dist: pyjwt (>=2.8.0,<3.0.0)
Requires-Dist: requests (>=2.31.0,<3.0.0)
Requires-Dist: requests-cache (>=1.1.0,<2.0.0)
Requires-Dist: sseclient-py (>=1.8.0,<2.0.0)
Requires-Dist: starlette (>=0.40.0,<0.47.0)
Requires-Dist: uvicorn (>=0.24.0,<0.25.0)
Requires-Dist: websocket-client (>=1.7.0,<2.0.0)
Project-URL: Documentation, https://agent-uri.readthedocs.io
Project-URL: Homepage, https://github.com/WizardOfAgents/agent-uri
Project-URL: Repository, https://github.com/WizardOfAgents/agent-uri
